sparsemax/__init__.py
sparsemax/sparsemax.py
sparsemax/utils.py
sparsemax-0.1.9.dist-info/AUTHORS.rst
sparsemax-0.1.9.dist-info/LICENSE
sparsemax-0.1.9.dist-info/METADATA
sparsemax-0.1.9.dist-info/WHEEL
sparsemax-0.1.9.dist-info/top_level.txt
sparsemax-0.1.9.dist-info/RECORD
