Metadata-Version: 2.1
Name: sparsemax
Version: 0.1.9
Summary: Sparsemax pytorch
Home-page: https://github.com/aced125/sparsemax
Author: Laksh Aithani
Author-email: lakshaithanii@gmail.com
License: MIT license
Keywords: sparsemax
Platform: UNKNOWN
Classifier: Development Status :: 2 - Pre-Alpha
Classifier: Intended Audience :: Developers
Classifier: License :: OSI Approved :: MIT License
Classifier: Natural Language :: English
Classifier: Programming Language :: Python :: 3
Classifier: Programming Language :: Python :: 3.5
Classifier: Programming Language :: Python :: 3.6
Classifier: Programming Language :: Python :: 3.7
Classifier: Programming Language :: Python :: 3.8
Requires-Python: >=3.5
Requires-Dist: torch
